bigdata_sampler/__init__.py
bigdata_sampler/sampler.py
bigdata_sampler_toolkit-0.1.3.dist-info/licenses/LICENSE
bigdata_sampler_toolkit-0.1.3.dist-info/METADATA
bigdata_sampler_toolkit-0.1.3.dist-info/WHEEL
bigdata_sampler_toolkit-0.1.3.dist-info/top_level.txt
bigdata_sampler_toolkit-0.1.3.dist-info/RECORD
