Metadata-Version: 2.4
Name: bigdata-sampler-toolkit
Version: 0.1.3
Summary: A Python package for sampling large datasets like CSV, JSON, Parquet, ORC, and Avro
Author-email: Ragul A <Ragulcom33@gmail.com>
License-Expression: MIT
Requires-Python: >=3.8
License-File: LICENSE
Requires-Dist: pandas>=2.0.0
Requires-Dist: pyarrow>=15.0.0
Requires-Dist: fastavro>=1.9.0
Dynamic: license-file
